s2k/__init__.py
s2k/config.py
s2k-1.0.dist-info/DESCRIPTION.rst
s2k-1.0.dist-info/LICENSE.txt
s2k-1.0.dist-info/METADATA
s2k-1.0.dist-info/RECORD
s2k-1.0.dist-info/WHEEL
s2k-1.0.dist-info/entry_points.txt
s2k-1.0.dist-info/metadata.json
s2k-1.0.dist-info/top_level.txt
