Metadata-Version: 2.0
Name: s2k
Version: 1.0
Summary: Send files to your Kindle email.
Home-page: https://github.com/hadenpike/s2k
Author: Haden Pike
Author-email: haden.pike@gmail.com
License: MIT
Download-URL: https://github.com/hadenpike/s2k/tarball/1.0
Platform: UNKNOWN
Classifier: Development Status :: 3 - Alpha
Classifier: Intended Audience :: Developers
Classifier: Programming Language :: Python :: 3
Requires-Dist: configobj
